qnc_crud/__init__.py
qnc_crud/fields.py
qnc_crud/js_response.py
qnc_crud/multiform.py
qnc_crud/page_invalidation.py
qnc_crud/permissions.py
qnc_crud/urls.py
qnc_crud/static/qnc_crud/ajax_all_forms.js
qnc_crud/static/qnc_crud/jquery-3.4.1.min.js
qnc_crud/static/qnc_crud/qnc_crud.css
qnc_crud/static/qnc_crud/reload_if_necessary.js
qnc_crud/static/qnc_crud/reload_restoration.js
qnc_crud/static/qnc_crud/set_form_errors.js
qnc_crud/static/qnc_crud/smart_back_button.js
qnc_crud/static/qnc_crud/utils.js
qnc_crud/templates/qnc_crud/all_scripts_and_styles.html
qnc_crud/templates/qnc_crud/complete_form.html
qnc_crud/templates/qnc_crud/form_fields.html
qnc_crud/templates/qnc_crud/form_test.html
qnc_crud/templates/qnc_crud/login.html
qnc_crud/templates/qnc_crud/login_required.html
qnc_crud/templates/qnc_crud/not_currently_allowed.html
qnc_crud/templates/qnc_crud/permission_denied.html
qnc_crud/templates/qnc_crud/reload_if_necessary.html
qnc_crud/templates/qnc_crud/smart_back_button.html
qnc_crud/templates/qnc_crud/user_styles.html
qnc_crud/templatetags/phone_link.py
qnc_crud/templatetags/qnc_crud.py
qnc_crud/templatetags/__pycache__/phone_link.cpython-36.pyc
qnc_crud/templatetags/__pycache__/phone_link.cpython-37.pyc
qnc_crud/templatetags/__pycache__/qnc_crud.cpython-36.pyc
qnc_crud/templatetags/__pycache__/qnc_crud.cpython-37.pyc
qnc_crud/tests/__init__.py
qnc_crud/tests/test_permissions.py
qnc_crud/views/login.py
qnc_crud-3.0.4.dist-info/LICENSE
qnc_crud-3.0.4.dist-info/METADATA
qnc_crud-3.0.4.dist-info/WHEEL
qnc_crud-3.0.4.dist-info/top_level.txt
qnc_crud-3.0.4.dist-info/RECORD
