Metadata-Version: 2.1
Name: qnc-crud
Version: 3.0.4
Summary: A set of utilities/mini-frameworks for building CRUD apps with Django
Home-page: https://github.com/quadrant-newmedia/qnc_crud
Author: Alex Fischer
Author-email: alex@quadrant.net
License: UNKNOWN
Platform: UNKNOWN
Classifier: Programming Language :: Python :: 3
Classifier: License :: OSI Approved :: MIT License
Classifier: Operating System :: OS Independent
Requires-Python: >=3.6
Requires-Dist: Django (<3.1,>=2.2)
Requires-Dist: django-early-return (<1,>=0.0)
